l/__init__.py
l/_lscolors.py
l/_version.py
l/cli.py
l/core.py
l/project.py
l/tests/__init__.py
l/tests/test_cli.py
l/tests/test_core.py
l/tests/test_project.py
l-0.10.0.dist-info/DESCRIPTION.rst
l-0.10.0.dist-info/METADATA
l-0.10.0.dist-info/RECORD
l-0.10.0.dist-info/WHEEL
l-0.10.0.dist-info/entry_points.txt
l-0.10.0.dist-info/metadata.json
l-0.10.0.dist-info/top_level.txt
